pycourseprogress/__init__.py
pycourseprogress/_version.py
pycourseprogress/api.py
pycourseprogress/classes.py
pycourseprogress/const.py
pycourseprogress/exceptions.py
pycourseprogress/member.py
pycourseprogress/py.typed
pycourseprogress-0.0.2.dist-info/LICENSE
pycourseprogress-0.0.2.dist-info/METADATA
pycourseprogress-0.0.2.dist-info/WHEEL
pycourseprogress-0.0.2.dist-info/entry_points.txt
pycourseprogress-0.0.2.dist-info/top_level.txt
pycourseprogress-0.0.2.dist-info/RECORD
