Metadata-Version: 2.1
Name: pycourseprogress
Version: 0.0.2
Summary: An integration for Course Progress sites.
Home-page: http://github.com/pantherale0/pycourseprogress
Author: pantherale0
License: MIT
Classifier: Programming Language :: Python :: 3
Classifier: License :: OSI Approved :: MIT License
Classifier: Operating System :: OS Independent
Requires-Python: >=3.8, <4
License-File: LICENSE
Requires-Dist: pyjwt ==2.*
Provides-Extra: dev
Requires-Dist: bandit ==1.7.* ; extra == 'dev'
Requires-Dist: black ==23.* ; extra == 'dev'
Requires-Dist: build ==0.10.* ; extra == 'dev'
Requires-Dist: flake8 ==6.* ; extra == 'dev'
Requires-Dist: isort ==5.* ; extra == 'dev'
Requires-Dist: mypy ==1.5.* ; extra == 'dev'
Requires-Dist: pytest ==7.* ; extra == 'dev'
Requires-Dist: pytest-cov ==4.* ; extra == 'dev'
Requires-Dist: twine ==4.* ; extra == 'dev'
Requires-Dist: pyjwt ==2.* ; extra == 'dev'
